reportportal_client/__init__.py
reportportal_client/errors.py
reportportal_client/service.py
reportportal_client/service_async.py
reportportal_client_eci-2.2.3.dist-info/LICENSE.md
reportportal_client_eci-2.2.3.dist-info/METADATA
reportportal_client_eci-2.2.3.dist-info/WHEEL
reportportal_client_eci-2.2.3.dist-info/top_level.txt
reportportal_client_eci-2.2.3.dist-info/RECORD
