Metadata-Version: 2.1
Name: reportportal-client-eci
Version: 2.2.3
Summary: Python client for Report Portal
Home-page: https://github.com/reportportal/client-Python
Author: Artsiom Tkachou
Author-email: SupportEPMC-TSTReportPortal@epam.com
License: Apache 2.0.
Download-URL: https://github.com/reportportal/client-Python/tarball/2.2.3
Keywords: testing,reporting,reportportal
Platform: UNKNOWN
Requires-Dist: requests (>=2.4.2)
Requires-Dist: six
